src/__init__.py
src/__main__.py
src/config.py
src/genetics/__init__.py
src/genetics/allele.py
src/genetics/gene.py
src/hardy_weinberg/__init__.py
src/hardy_weinberg/hardy_weinberg.py
src/hardy_weinberg/hardy_weinberg_stats.py
src/utils/__init__.py
src/utils/generators/__init__.py
src/utils/generators/char_generator.py
src/utils/generators/population_generator.py
src/utils/parsers/__init__.py
src/utils/parsers/args_parser.py
hardyweinbergcalculator-0.3.6.dist-info/LICENSE
hardyweinbergcalculator-0.3.6.dist-info/METADATA
hardyweinbergcalculator-0.3.6.dist-info/WHEEL
hardyweinbergcalculator-0.3.6.dist-info/entry_points.txt
hardyweinbergcalculator-0.3.6.dist-info/top_level.txt
hardyweinbergcalculator-0.3.6.dist-info/RECORD
