Metadata-Version: 2.1
Name: hardyweinbergcalculator
Version: 0.3.6
Summary: Hardy-Weinberg Equilibrium Calculator. Calculates the expected genotype frequencies based on the allele frequencies of a population in Hardy-Weinberg equilibrium.
Home-page: https://github.com/dellius-alexander/Hardy-Weinberg.git
Author: Dellius Alexander
Author-email: info@hyfisolutions.com
Maintainer: info@hyfisolutions.com
Maintainer-email: info@hyfisolutions.com
License: MIT License
Keywords: hardy-weinberg-equilibrium,hardy-weinberg-equilibrium-calculator,hardy-weinberg-calculator,chi-square,chi-square-test
Platform: UNKNOWN
Classifier: Development Status :: 5 - Production/Stable
Classifier: Intended Audience :: Developers
Classifier: License :: OSI Approved :: MIT License
Classifier: Operating System :: OS Independent
Classifier: Programming Language :: Python :: 3.7
Classifier: Programming Language :: Python :: Implementation :: CPython
Classifier: Programming Language :: Python :: Implementation :: PyPy
Requires-Python: >=3.7
License-File: LICENSE
Requires-Dist: sympy
Requires-Dist: numpy
Requires-Dist: matplotlib
Requires-Dist: pandas
